{
    "backend": "flask",
    "db_name": "",
    "db_pass": "",
    "db_type": "sqlite",
    "db_user": "",
    "dbms": "1",
    "description": "generated product",
    "design": "material-dashboard",
    "docker": "0",
    "err_code": 0,
    "frontend": "",
    "heroku": "0",
    "pattern": "mvc",
    "pro": "0",
    "task_id": "a8f8f38f-7999-42d0-95fb-e13709e8189f",
    "task_info": "Upload Sources [0%] - 369 files",
    "task_output": "a8f8f38f-7999-42d0-95fb-e13709e8189f.zip",
    "task_result": "SUCCESS",
    "task_state": "RUNNING",
    "task_ts_end": "2024-12-31-09-40-52",
    "task_ts_start": "2024-12-31-09-40-49"
}